Metadata-Version: 1.1
Name: fake-useragent-ex
Version: 0.1.12
Summary: Up to date simple useragent faker with real world database
Home-page: https://github.com/hellysmile/fake-useragent
Author: hellysmile@gmail.com
Author-email: hellysmile@gmail.com
License: UNKNOWN
Keywords: user,agent,user agent,useragent,fake,fake useragent,fake user agent
Platform: UNKNOWN
Classifier: Development Status :: 5 - Production/Stable
Classifier: Intended Audience :: Developers
Classifier: License :: OSI Approved :: Apache Software License
Classifier: Operating System :: POSIX
Classifier: Operating System :: MacOS :: MacOS X
Classifier: Operating System :: Microsoft :: Windows
Classifier: Programming Language :: Python
Classifier: Programming Language :: Python :: 2
Classifier: Programming Language :: Python :: 3
Classifier: Operating System :: OS Independent
